wagtailembedder/__init__.py
wagtailembedder/format.py
wagtailembedder/helper.py
wagtailembedder/urls.py
wagtailembedder/wagtail_hooks.py
wagtailembedder/static/wagtailembedder/css/admin.css
wagtailembedder/static/wagtailembedder/js/hallo-embedder.js
wagtailembedder/templates/wagtailembedder/editor/embed_editor.html
wagtailembedder/templates/wagtailembedder/editor/snippet_chosen.js
wagtailembedder/templates/wagtailembedder/snippets/type_index.html
wagtailembedder/templates/wagtailembedder/snippets/type_index.js
wagtailembedder/templates/wagtailembedder/snippets/types_list.html
wagtailembedder/templates/wagtailembedder/snippets/types_list.js
wagtailembedder/views/__init__.py
wagtailembedder/views/chooser.py
wagtailembedder/views/snippets.py
wagtailembedder-1.1.dist-info/DESCRIPTION.rst
wagtailembedder-1.1.dist-info/METADATA
wagtailembedder-1.1.dist-info/RECORD
wagtailembedder-1.1.dist-info/WHEEL
wagtailembedder-1.1.dist-info/metadata.json
wagtailembedder-1.1.dist-info/top_level.txt
